DrMoriaty/__init__.py
DrMoriaty/setting.py
DrMoriaty/cmd/__init__.py
DrMoriaty/cmd/main.py
DrMoriaty/datas/__init__.py
DrMoriaty/datas/data.py
DrMoriaty/dolch/__init__.py
DrMoriaty/dolch/dolch.py
DrMoriaty/dolch/joker.py
DrMoriaty/dolch/jsp.py
DrMoriaty/dolch/lib.py
DrMoriaty/dolch/php.py
DrMoriaty/dolch/sword.py
DrMoriaty/masscan/__init__.py
DrMoriaty/masscan/masscan.py
DrMoriaty/nico/__init__.py
DrMoriaty/nico/libs.py
DrMoriaty/nico/proxy2.py
DrMoriaty/nico/sniffer.py
DrMoriaty/searcher/__init__.py
DrMoriaty/searcher/fofa_search.py
DrMoriaty/searcher/github_search.py
DrMoriaty/sherlock/__init__.py
DrMoriaty/sherlock/libs.py
DrMoriaty/sherlock/test.py
DrMoriaty/utils/__init__.py
DrMoriaty/utils/daemon.py
DrMoriaty/utils/log.py
x_mroy_1051-0.2.2.dist-info/METADATA
x_mroy_1051-0.2.2.dist-info/RECORD
x_mroy_1051-0.2.2.dist-info/WHEEL
x_mroy_1051-0.2.2.dist-info/entry_points.txt
x_mroy_1051-0.2.2.dist-info/top_level.txt
